{
  "_comment": "slug -> easylaw.go.kr URL 매핑. csmSeq: 233=이혼, 255=상속, 234=유언",
  "_toc": {
    "이혼": "https://easylaw.go.kr/CSP/CnpClsMain.laf?csmSeq=233&ccfNo=1&cciNo=1&cnpClsNo=1",
    "상속": "https://easylaw.go.kr/CSP/CnpClsMain.laf?csmSeq=255&ccfNo=1&cciNo=1&cnpClsNo=1",
    "국민건강보험(직장가입자)": "https://easylaw.go.kr/CSP/CnpClsMain.laf?csmSeq=1063&ccfNo=1&cciNo=1&cnpClsNo=1"
  },
  "협의이혼-절차-서류-이혼숙려기간": [
    "https://easylaw.go.kr/CSP/CnpClsMain.laf?csmSeq=233&ccfNo=2&cciNo=2&cnpClsNo=1",
    "https://easylaw.go.kr/CSP/CnpClsMain.laf?csmSeq=233&ccfNo=2&cciNo=1&cnpClsNo=1",
    "https://easylaw.go.kr/CSP/CnpClsMain.laf?csmSeq=233&ccfNo=2&cciNo=1&cnpClsNo=2"
  ],
  "재판상이혼-사유-부정행위-가정폭력": [
    "https://easylaw.go.kr/CSP/CnpClsMain.laf?csmSeq=233&ccfNo=3&cciNo=1&cnpClsNo=1",
    "https://easylaw.go.kr/CSP/CnpClsMain.laf?csmSeq=233&ccfNo=3&cciNo=1&cnpClsNo=2"
  ],
  "산업재해보상보험-개념-특징-적용범위": [
    "https://easylaw.go.kr/CSP/CnpClsMain.laf?csmSeq=575&ccfNo=1&cciNo=1&cnpClsNo=1"
  ],
  "산재보험-보험급여-종류-요양급여-휴업급여": [
    "https://easylaw.go.kr/CSP/CnpClsMain.laf?csmSeq=575&ccfNo=1&cciNo=1&cnpClsNo=2"
  ],
  "산재보험-요양급여-지급요건-범위-산정기준": [
    "https://easylaw.go.kr/CSP/CnpClsMain.laf?csmSeq=575&ccfNo=2&cciNo=2&cnpClsNo=1"
  ],
  "산재보험-일괄적용-도급사업-건설업-사업주": [
    "https://easylaw.go.kr/CSP/CnpClsMain.laf?csmSeq=570&ccfNo=2&cciNo=2&cnpClsNo=2"
  ],
  "산재보험료-징수-보험료율-개별실적요율-산정": [
    "https://easylaw.go.kr/CSP/CnpClsMain.laf?csmSeq=570&ccfNo=2&cciNo=2&cnpClsNo=3"
  ],
  "산재보험-국외사업-해외파견자-특례-가입": [
    "https://easylaw.go.kr/CSP/CnpClsMain.laf?csmSeq=570&ccfNo=2&cciNo=3&cnpClsNo=1",
    "https://easylaw.go.kr/CSP/CnpClsMain.laf?csmSeq=570&ccfNo=2&cciNo=3&cnpClsNo=2"
  ],
  "산재보험-현장실습생-중소기업-사업주-특례": [
    "https://easylaw.go.kr/CSP/CnpClsMain.laf?csmSeq=570&ccfNo=2&cciNo=3&cnpClsNo=3",
    "https://easylaw.go.kr/CSP/CnpClsMain.laf?csmSeq=570&ccfNo=2&cciNo=3&cnpClsNo=4"
  ],
  "산재보험-자활급여-수급자-노무제공자-특례": [
    "https://easylaw.go.kr/CSP/CnpClsMain.laf?csmSeq=570&ccfNo=2&cciNo=3&cnpClsNo=5",
    "https://easylaw.go.kr/CSP/CnpClsMain.laf?csmSeq=570&ccfNo=2&cciNo=3&cnpClsNo=6"
  ],
  "산재-근골격계질병-인정기준-반복동작-업무상질병": [
    "https://easylaw.go.kr/CSP/CnpClsMain.laf?csmSeq=570&ccfNo=4&cciNo=2&cnpClsNo=3"
  ],
  "산재-호흡기-신경정신-림프조혈기-질병-인정기준": [
    "https://easylaw.go.kr/CSP/CnpClsMain.laf?csmSeq=570&ccfNo=4&cciNo=2&cnpClsNo=4"
  ],
  "산재-피부-눈-귀-간-감염성-질병-인정기준": [
    "https://easylaw.go.kr/CSP/CnpClsMain.laf?csmSeq=570&ccfNo=4&cciNo=2&cnpClsNo=5",
    "https://easylaw.go.kr/CSP/CnpClsMain.laf?csmSeq=570&ccfNo=4&cciNo=2&cnpClsNo=6"
  ],
  "산재-직업성암-화학적-물리적-요인-질병-인정기준": [
    "https://easylaw.go.kr/CSP/CnpClsMain.laf?csmSeq=570&ccfNo=4&cciNo=2&cnpClsNo=7",
    "https://easylaw.go.kr/CSP/CnpClsMain.laf?csmSeq=570&ccfNo=4&cciNo=2&cnpClsNo=8",
    "https://easylaw.go.kr/CSP/CnpClsMain.laf?csmSeq=570&ccfNo=4&cciNo=2&cnpClsNo=9"
  ],
  "국민건강보험-개념-특성-적용대상": [
    "https://easylaw.go.kr/CSP/CnpClsMain.laf?csmSeq=1063&ccfNo=1&cciNo=1&cnpClsNo=1"
  ],
  "직장가입자-가입자격-취득-신고": [
    "https://easylaw.go.kr/CSP/CnpClsMain.laf?csmSeq=1063&ccfNo=2&cciNo=1&cnpClsNo=1"
  ],
  "직장가입자-자격변동-상실-신고": [
    "https://easylaw.go.kr/CSP/CnpClsMain.laf?csmSeq=1063&ccfNo=2&cciNo=1&cnpClsNo=2"
  ],
  "임의계속가입-실업자-직장가입자-자격유지": [
    "https://easylaw.go.kr/CSP/CnpClsMain.laf?csmSeq=1063&ccfNo=2&cciNo=1&cnpClsNo=3"
  ],
  "건강보험증-발급-제출-부정수급-금지": [
    "https://easylaw.go.kr/CSP/CnpClsMain.laf?csmSeq=1063&ccfNo=2&cciNo=2&cnpClsNo=1"
  ],
  "요양급여-비급여-범위-요양기관": [
    "https://easylaw.go.kr/CSP/CnpClsMain.laf?csmSeq=1063&ccfNo=3&cciNo=1&cnpClsNo=1"
  ],
  "본인일부부담금-부담률-상한액-납부": [
    "https://easylaw.go.kr/CSP/CnpClsMain.laf?csmSeq=1063&ccfNo=3&cciNo=1&cnpClsNo=2"
  ],
  "요양비-현금급여-수급-신청방법": [
    "https://easylaw.go.kr/CSP/CnpClsMain.laf?csmSeq=1063&ccfNo=3&cciNo=2&cnpClsNo=1"
  ],
  "임신출산-진료비-국민행복카드-지원금액": [
    "https://easylaw.go.kr/CSP/CnpClsMain.laf?csmSeq=1063&ccfNo=3&cciNo=3&cnpClsNo=1"
  ],
  "장애인-보조기기-보험급여-지원기준": [
    "https://easylaw.go.kr/CSP/CnpClsMain.laf?csmSeq=1063&ccfNo=3&cciNo=4&cnpClsNo=1"
  ],
  "건강보험-건강검진-종류-대상-비용": [
    "https://easylaw.go.kr/CSP/CnpClsMain.laf?csmSeq=1063&ccfNo=3&cciNo=5&cnpClsNo=1"
  ],
  "건강보험급여-제한-지급정지-사유": [
    "https://easylaw.go.kr/CSP/CnpClsMain.laf?csmSeq=1063&ccfNo=3&cciNo=6&cnpClsNo=1"
  ],
  "건강보험료-산정-보수월액-보험료율": [
    "https://easylaw.go.kr/CSP/CnpClsMain.laf?csmSeq=1063&ccfNo=4&cciNo=1&cnpClsNo=1"
  ],
  "건강보험료-경감-면제-사유-경감률": [
    "https://easylaw.go.kr/CSP/CnpClsMain.laf?csmSeq=1063&ccfNo=4&cciNo=1&cnpClsNo=2"
  ],
  "건강보험료-납부-정산-부담-방법": [
    "https://easylaw.go.kr/CSP/CnpClsMain.laf?csmSeq=1063&ccfNo=4&cciNo=1&cnpClsNo=3"
  ],
  "건강보험료-체납-연체금-독촉-처분": [
    "https://easylaw.go.kr/CSP/CnpClsMain.laf?csmSeq=1063&ccfNo=4&cciNo=1&cnpClsNo=4"
  ],
  "건강보험-이의신청-심판청구-방법": [
    "https://easylaw.go.kr/CSP/CnpClsMain.laf?csmSeq=1063&ccfNo=5&cciNo=1&cnpClsNo=1"
  ],
  "이혼조정-신청-비용-재판이혼-기간": [
    "https://easylaw.go.kr/CSP/CnpClsMain.laf?csmSeq=233&ccfNo=3&cciNo=2&cnpClsNo=1"
  ],
  "재산분할-대상-퇴직금-연금-채무": [
    "https://easylaw.go.kr/CSP/CnpClsMain.laf?csmSeq=233&ccfNo=4&cciNo=2&cnpClsNo=1",
    "https://easylaw.go.kr/CSP/CnpClsMain.laf?csmSeq=233&ccfNo=4&cciNo=2&cnpClsNo=2"
  ],
  "재산분할-비율-기여도-혼인기간": [
    "https://easylaw.go.kr/CSP/CnpClsMain.laf?csmSeq=233&ccfNo=4&cciNo=2&cnpClsNo=1",
    "https://easylaw.go.kr/CSP/CnpClsMain.laf?csmSeq=233&ccfNo=4&cciNo=2&cnpClsNo=2"
  ],
  "재산분할청구권-소멸시효-2년": [
    "https://easylaw.go.kr/CSP/CnpClsMain.laf?csmSeq=233&ccfNo=4&cciNo=2&cnpClsNo=4"
  ],
  "이혼-재산분할-양도소득세-취득세": [
    "https://easylaw.go.kr/CSP/CnpClsMain.laf?csmSeq=233&ccfNo=4&cciNo=2&cnpClsNo=5"
  ],
  "이혼-위자료-금액-유책배우자": [
    "https://easylaw.go.kr/CSP/CnpClsMain.laf?csmSeq=233&ccfNo=4&cciNo=1&cnpClsNo=1",
    "https://easylaw.go.kr/CSP/CnpClsMain.laf?csmSeq=233&ccfNo=4&cciNo=1&cnpClsNo=2"
  ],
  "이혼-위자료-재산분할-차이점": [
    "https://easylaw.go.kr/CSP/CnpClsMain.laf?csmSeq=233&ccfNo=4&cciNo=1&cnpClsNo=1",
    "https://easylaw.go.kr/CSP/CnpClsMain.laf?csmSeq=233&ccfNo=4&cciNo=2&cnpClsNo=1",
    "https://easylaw.go.kr/CSP/CnpClsMain.laf?csmSeq=233&ccfNo=1&cciNo=3&cnpClsNo=1"
  ],
  "협의이혼-친권자-지정-재판이혼": [
    "https://easylaw.go.kr/CSP/CnpClsMain.laf?csmSeq=233&ccfNo=5&cciNo=1&cnpClsNo=1",
    "https://easylaw.go.kr/CSP/CnpClsMain.laf?csmSeq=233&ccfNo=2&cciNo=1&cnpClsNo=2"
  ],
  "이혼-양육권-판단기준-지정방법": [
    "https://easylaw.go.kr/CSP/CnpClsMain.laf?csmSeq=233&ccfNo=5&cciNo=1&cnpClsNo=2"
  ],
  "이혼-양육비-산정기준표-소득": [
    "https://easylaw.go.kr/CSP/CnpClsMain.laf?csmSeq=233&ccfNo=5&cciNo=3&cnpClsNo=1"
  ],
  "양육비-미지급-이행명령-직접지급": [
    "https://easylaw.go.kr/CSP/CnpClsMain.laf?csmSeq=233&ccfNo=5&cciNo=3&cnpClsNo=3"
  ],
  "친권-양육권-차이-분리지정": [
    "https://easylaw.go.kr/CSP/CnpClsMain.laf?csmSeq=233&ccfNo=5&cciNo=1&cnpClsNo=1",
    "https://easylaw.go.kr/CSP/CnpClsMain.laf?csmSeq=233&ccfNo=5&cciNo=1&cnpClsNo=2"
  ],
  "면접교섭권-거부-이행강제": [
    "https://easylaw.go.kr/CSP/CnpClsMain.laf?csmSeq=233&ccfNo=5&cciNo=2&cnpClsNo=1",
    "https://easylaw.go.kr/CSP/CnpClsMain.laf?csmSeq=233&ccfNo=5&cciNo=2&cnpClsNo=2"
  ],
  "이혼후-자녀-성본변경-재혼": [
    "https://easylaw.go.kr/CSP/CnpClsMain.laf?csmSeq=233&ccfNo=5&cciNo=4&cnpClsNo=1",
    "https://easylaw.go.kr/CSP/CnpClsMain.laf?csmSeq=233&ccfNo=5&cciNo=4&cnpClsNo=2"
  ],
  "가정폭력-이혼소송-증거-양육권": [
    "https://easylaw.go.kr/CSP/CnpClsMain.laf?csmSeq=233&ccfNo=6&cciNo=2&cnpClsNo=1",
    "https://easylaw.go.kr/CSP/CnpClsMain.laf?csmSeq=233&ccfNo=6&cciNo=2&cnpClsNo=2"
  ],
  "사실혼-파기-재산분할-위자료": [
    "https://easylaw.go.kr/CSP/CnpClsMain.laf?csmSeq=233&ccfNo=1&cciNo=1&cnpClsNo=2",
    "https://easylaw.go.kr/CSP/CnpClsMain.laf?csmSeq=233&ccfNo=1&cciNo=5&cnpClsNo=1",
    "https://easylaw.go.kr/CSP/CnpClsMain.laf?csmSeq=233&ccfNo=1&cciNo=5&cnpClsNo=2",
    "https://easylaw.go.kr/CSP/CnpClsMain.laf?csmSeq=233&ccfNo=1&cciNo=5&cnpClsNo=3"
  ],
  "협의이혼-취소-무효-이혼의사철회": [
    "https://easylaw.go.kr/CSP/CnpClsMain.laf?csmSeq=233&ccfNo=1&cciNo=4&cnpClsNo=1",
    "https://easylaw.go.kr/CSP/CnpClsMain.laf?csmSeq=233&ccfNo=1&cciNo=4&cnpClsNo=2",
    "https://easylaw.go.kr/CSP/CnpClsMain.laf?csmSeq=233&ccfNo=2&cciNo=2&cnpClsNo=2"
  ],
  "유책배우자-이혼청구-별거-혼인파탄": [
    "https://easylaw.go.kr/CSP/CnpClsMain.laf?csmSeq=233&ccfNo=3&cciNo=1&cnpClsNo=3",
    "https://easylaw.go.kr/CSP/CnpClsMain.laf?csmSeq=233&ccfNo=4&cciNo=2&cnpClsNo=3"
  ],
  "사실상-이혼-법적-효력-중혼": [
    "https://easylaw.go.kr/CSP/CnpClsMain.laf?csmSeq=233&ccfNo=1&cciNo=1&cnpClsNo=3"
  ],
  "이혼소송-전-증거-수집-가압류": [
    "https://easylaw.go.kr/CSP/CnpClsMain.laf?csmSeq=233&ccfNo=1&cciNo=2&cnpClsNo=1",
    "https://easylaw.go.kr/CSP/CnpClsMain.laf?csmSeq=233&ccfNo=3&cciNo=2&cnpClsNo=4"
  ],
  "이혼소송-피고-답변서-응소": [
    "https://easylaw.go.kr/CSP/CnpClsMain.laf?csmSeq=233&ccfNo=1&cciNo=2&cnpClsNo=3"
  ],
  "이혼-후-인척관계-소멸-재혼-제한": [
    "https://easylaw.go.kr/CSP/CnpClsMain.laf?csmSeq=233&ccfNo=1&cciNo=3&cnpClsNo=2"
  ],
  "이혼신고-무효-사유-확인소송": [
    "https://easylaw.go.kr/CSP/CnpClsMain.laf?csmSeq=233&ccfNo=1&cciNo=4&cnpClsNo=1"
  ],
  "이혼-취소-사기-강박-제척기간": [
    "https://easylaw.go.kr/CSP/CnpClsMain.laf?csmSeq=233&ccfNo=1&cciNo=4&cnpClsNo=2"
  ],
  "사실혼-재산분할-청구권-소멸시효": [
    "https://easylaw.go.kr/CSP/CnpClsMain.laf?csmSeq=233&ccfNo=1&cciNo=5&cnpClsNo=3"
  ],
  "사실혼-자녀-양육비-인지-절차": [
    "https://easylaw.go.kr/CSP/CnpClsMain.laf?csmSeq=233&ccfNo=1&cciNo=5&cnpClsNo=4",
    "https://easylaw.go.kr/CSP/CnpClsMain.laf?csmSeq=233&ccfNo=1&cciNo=5&cnpClsNo=1"
  ],
  "협의이혼-양육협의서-양육비부담조서": [
    "https://easylaw.go.kr/CSP/CnpClsMain.laf?csmSeq=233&ccfNo=2&cciNo=1&cnpClsNo=2"
  ],
  "협의이혼-재산합의-구속력-번복": [
    "https://easylaw.go.kr/CSP/CnpClsMain.laf?csmSeq=233&ccfNo=2&cciNo=1&cnpClsNo=3"
  ],
  "해외거주-한국인-협의이혼-재외공관": [
    "https://easylaw.go.kr/CSP/CnpClsMain.laf?csmSeq=233&ccfNo=2&cciNo=2&cnpClsNo=3"
  ],
  "협의이혼-위자료-미합의-소멸시효": [
    "https://easylaw.go.kr/CSP/CnpClsMain.laf?csmSeq=233&ccfNo=4&cciNo=1&cnpClsNo=3",
    "https://easylaw.go.kr/CSP/CnpClsMain.laf?csmSeq=233&ccfNo=2&cciNo=1&cnpClsNo=3"
  ],
  "재산분할-재산명시-재산조회-제도": [
    "https://easylaw.go.kr/CSP/CnpClsMain.laf?csmSeq=233&ccfNo=4&cciNo=2&cnpClsNo=6"
  ],
  "친권자-양육자-변경-사유-심판": [
    "https://easylaw.go.kr/CSP/CnpClsMain.laf?csmSeq=233&ccfNo=5&cciNo=1&cnpClsNo=3"
  ],
  "친권-상실-선고-후견인-지정": [
    "https://easylaw.go.kr/CSP/CnpClsMain.laf?csmSeq=233&ccfNo=5&cciNo=1&cnpClsNo=1"
  ],
  "양육비-증액-감액-사정변경": [
    "https://easylaw.go.kr/CSP/CnpClsMain.laf?csmSeq=233&ccfNo=5&cciNo=3&cnpClsNo=1",
    "https://easylaw.go.kr/CSP/CnpClsMain.laf?csmSeq=233&ccfNo=5&cciNo=3&cnpClsNo=3"
  ],
  "양육비-대지급-양육비이행관리원": [
    "https://easylaw.go.kr/CSP/CnpClsMain.laf?csmSeq=233&ccfNo=5&cciNo=3&cnpClsNo=3"
  ],
  "면접교섭권-제한-배제-심판": [
    "https://easylaw.go.kr/CSP/CnpClsMain.laf?csmSeq=233&ccfNo=5&cciNo=2&cnpClsNo=1",
    "https://easylaw.go.kr/CSP/CnpClsMain.laf?csmSeq=233&ccfNo=5&cciNo=2&cnpClsNo=2"
  ],
  "가정폭력-고소-보호처분-접근금지": [
    "https://easylaw.go.kr/CSP/CnpClsMain.laf?csmSeq=233&ccfNo=6&cciNo=2&cnpClsNo=1",
    "https://easylaw.go.kr/CSP/CnpClsMain.laf?csmSeq=233&ccfNo=6&cciNo=2&cnpClsNo=2"
  ],
  "이혼결심-협의이혼-재판이혼-비교": [
    "https://easylaw.go.kr/CSP/CnpClsMain.laf?csmSeq=233&ccfNo=1&cciNo=1&cnpClsNo=1",
    "https://easylaw.go.kr/CSP/CnpClsMain.laf?csmSeq=233&ccfNo=1&cciNo=2&cnpClsNo=1",
    "https://easylaw.go.kr/CSP/CnpClsMain.laf?csmSeq=233&ccfNo=1&cciNo=2&cnpClsNo=2"
  ],
  "national-health-insurance-regional-subscriber-target": [
    "https://www.easylaw.go.kr/CSP/CnpClsMain.laf?csmSeq=1141&ccfNo=1&cciNo=1&cnpClsNo=1"
  ],
  "health-insurance-regional-subscriber-qualification": [
    "https://www.easylaw.go.kr/CSP/CnpClsMain.laf?csmSeq=1141&ccfNo=2&cciNo=1&cnpClsNo=1"
  ],
  "health-insurance-regional-qualification-change": [
    "https://www.easylaw.go.kr/CSP/CnpClsMain.laf?csmSeq=1141&ccfNo=2&cciNo=1&cnpClsNo=2"
  ],
  "sangsokpogi-seoryu-mokrok-gajeonbeopwon-singyo": [
    "https://easylaw.go.kr/CSP/CnpClsMain.laf?csmSeq=255&ccfNo=4&cciNo=4&cnpClsNo=1"
  ],
  "hanjeongseugin-singyo-seoryu-jaesanmokrok": [
    "https://easylaw.go.kr/CSP/CnpClsMain.laf?csmSeq=255&ccfNo=4&cciNo=3&cnpClsNo=1"
  ],
  "hanjeongseugin-sangsokpogi-chai-husunwi-bigyo": [
    "https://easylaw.go.kr/CSP/CnpClsMain.laf?csmSeq=255&ccfNo=4&cciNo=1&cnpClsNo=1",
    "https://easylaw.go.kr/CSP/CnpClsMain.laf?csmSeq=255&ccfNo=4&cciNo=3&cnpClsNo=1",
    "https://easylaw.go.kr/CSP/CnpClsMain.laf?csmSeq=255&ccfNo=4&cciNo=4&cnpClsNo=1"
  ],
  "teukbyeol-hanjeongseugin-singyo-yogeon": [
    "https://easylaw.go.kr/CSP/CnpClsMain.laf?csmSeq=255&ccfNo=4&cciNo=3&cnpClsNo=1",
    "https://easylaw.go.kr/CSP/CnpClsMain.laf?csmSeq=255&ccfNo=4&cciNo=2&cnpClsNo=1"
  ],
  "sangsokse-gichocongje-iljalgongje-baeujaigongje": [
    "https://easylaw.go.kr/CSP/CnpClsMain.laf?csmSeq=255&ccfNo=7&cciNo=2&cnpClsNo=1"
  ],
  "sangsokse-seyul-guwon-gyesan-gwasepyojun": [
    "https://easylaw.go.kr/CSP/CnpClsMain.laf?csmSeq=255&ccfNo=7&cciNo=2&cnpClsNo=1"
  ],
  "sangsokse-singyo-gihan-misingo-gasanse": [
    "https://easylaw.go.kr/CSP/CnpClsMain.laf?csmSeq=255&ccfNo=7&cciNo=2&cnpClsNo=1"
  ],
  "yurubun-hwanwancheongu-somelsiyo-saengjeon-jeungyeo": [
    "https://easylaw.go.kr/CSP/CnpClsMain.laf?csmSeq=255&ccfNo=6&cciNo=1&cnpClsNo=1"
  ],
  "yurubun-biyul-jikyebisok-baeuija-hyeongje": [
    "https://easylaw.go.kr/CSP/CnpClsMain.laf?csmSeq=255&ccfNo=6&cciNo=1&cnpClsNo=1"
  ],
  "beopjeong-sangsoksunwi-baeuija-janyeo": [
    "https://easylaw.go.kr/CSP/CnpClsMain.laf?csmSeq=255&ccfNo=2&cciNo=1&cnpClsNo=1",
    "https://easylaw.go.kr/CSP/CnpClsMain.laf?csmSeq=255&ccfNo=2&cciNo=1&cnpClsNo=2"
  ],
  "baeuija-dandoksangsok-yogeon-hobeom": [
    "https://easylaw.go.kr/CSP/CnpClsMain.laf?csmSeq=255&ccfNo=2&cciNo=1&cnpClsNo=1",
    "https://easylaw.go.kr/CSP/CnpClsMain.laf?csmSeq=255&ccfNo=2&cciNo=1&cnpClsNo=2"
  ],
  "sangsokdeunggi-seoryu-mokrok-cwiduksesingo": [
    "https://easylaw.go.kr/CSP/CnpClsMain.laf?csmSeq=255&ccfNo=7&cciNo=1&cnpClsNo=1",
    "https://easylaw.go.kr/CSP/CnpClsMain.laf?csmSeq=255&ccfNo=7&cciNo=2&cnpClsNo=2"
  ],
  "sangsokdeunggi-hyeobuibunhal-ingamjeungmyeong": [
    "https://easylaw.go.kr/CSP/CnpClsMain.laf?csmSeq=255&ccfNo=7&cciNo=1&cnpClsNo=1",
    "https://easylaw.go.kr/CSP/CnpClsMain.laf?csmSeq=255&ccfNo=3&cciNo=3&cnpClsNo=2"
  ],
  "sangsok-bunhalhyeobuiseo-jakseong-bangbeop": [
    "https://easylaw.go.kr/CSP/CnpClsMain.laf?csmSeq=255&ccfNo=3&cciNo=3&cnpClsNo=2"
  ],
  "sangsok-bunhalhyeobuiseo-gongjeon-ingam": [
    "https://easylaw.go.kr/CSP/CnpClsMain.laf?csmSeq=255&ccfNo=3&cciNo=3&cnpClsNo=2"
  ],
  "daesup-sangsok-yogeon-sonjanyeo-gyeolgyeok": [
    "https://easylaw.go.kr/CSP/CnpClsMain.laf?csmSeq=255&ccfNo=2&cciNo=1&cnpClsNo=2"
  ],
  "giyeobun-injeonggijun-sangsok-bunhal": [
    "https://easylaw.go.kr/CSP/CnpClsMain.laf?csmSeq=255&ccfNo=3&cciNo=2&cnpClsNo=3"
  ],
  "sangsok-chaemubeomwi-bozeungchaeumu-goyujaesan": [
    "https://easylaw.go.kr/CSP/CnpClsMain.laf?csmSeq=255&ccfNo=3&cciNo=1&cnpClsNo=1",
    "https://easylaw.go.kr/CSP/CnpClsMain.laf?csmSeq=255&ccfNo=4&cciNo=1&cnpClsNo=1"
  ],
  "sangsok-jaesan-johoe-geumyunggeorare": [
    "https://easylaw.go.kr/CSP/CnpClsMain.laf?csmSeq=255&ccfNo=1&cciNo=1&cnpClsNo=3",
    "https://easylaw.go.kr/CSP/CnpClsMain.laf?csmSeq=255&ccfNo=3&cciNo=1&cnpClsNo=1"
  ],
  "yueunjang-jongryu-hyoryeok-japiljeungseo": [
    "https://easylaw.go.kr/CSP/CnpClsMain.laf?csmSeq=234&ccfNo=1&cciNo=1&cnpClsNo=1"
  ],
  "sangsokse-yeonbuyeonnam-singyo-mulnam": [
    "https://easylaw.go.kr/CSP/CnpClsMain.laf?csmSeq=255&ccfNo=7&cciNo=2&cnpClsNo=1"
  ],
  "miseongnyeonja-sangsok-teukbyeoldaeriin": [
    "https://easylaw.go.kr/CSP/CnpClsMain.laf?csmSeq=255&ccfNo=3&cciNo=1&cnpClsNo=1"
  ],
  "sangsok-hoebokcheonggugwon-chamching-soson": [
    "https://easylaw.go.kr/CSP/CnpClsMain.laf?csmSeq=255&ccfNo=3&cciNo=4&cnpClsNo=1"
  ],
  "sangga-hwansan-bojeunggeum-jiyeokbyeol": [
    "https://easylaw.go.kr/CSP/CnpClsMain.laf?csmSeq=627&ccfNo=1&cciNo=2&cnpClsNo=1",
    "https://easylaw.go.kr/CSP/CnpClsMain.laf?csmSeq=627&ccfNo=1&cciNo=2&cnpClsNo=2"
  ],
  "sangga-saeupja-daehangnyeok-chwideuk-sijeom": [
    "https://easylaw.go.kr/CSP/CnpClsMain.laf?csmSeq=627&ccfNo=2&cciNo=3&cnpClsNo=1"
  ],
  "sangga-bojeunggeum-wolse-jeonhwan-yijaeyul": [
    "https://easylaw.go.kr/CSP/CnpClsMain.laf?csmSeq=627&ccfNo=3&cciNo=1&cnpClsNo=3",
    "https://easylaw.go.kr/CSP/CnpClsMain.laf?csmSeq=627&ccfNo=3&cciNo=1&cnpClsNo=2"
  ],
  "sangga-soaek-imsaigin-choeuiseon-byeoje": [
    "https://easylaw.go.kr/CSP/CnpClsMain.laf?csmSeq=627&ccfNo=4&cciNo=2&cnpClsNo=2",
    "https://easylaw.go.kr/CSP/CnpClsMain.laf?csmSeq=627&ccfNo=1&cciNo=2&cnpClsNo=1"
  ],
  "sangga-imdaein-maemae-imdaecha-seungge": [
    "https://easylaw.go.kr/CSP/CnpClsMain.laf?csmSeq=627&ccfNo=3&cciNo=3&cnpClsNo=2",
    "https://easylaw.go.kr/CSP/CnpClsMain.laf?csmSeq=627&ccfNo=2&cciNo=3&cnpClsNo=1"
  ],
  "jaegebal-imsisangga-ipju-jakyeok": [
    "https://easylaw.go.kr/CSP/CnpClsMain.laf?csmSeq=1168&ccfNo=3&cciNo=2&cnpClsNo=2",
    "https://easylaw.go.kr/CSP/CnpClsMain.laf?csmSeq=1168&ccfNo=3&cciNo=2&cnpClsNo=3"
  ],
  "jaegeonsuk-jaegebal-bosan-chai": [
    "https://easylaw.go.kr/CSP/CnpClsMain.laf?csmSeq=1168&ccfNo=1&cciNo=1&cnpClsNo=1",
    "https://easylaw.go.kr/CSP/CnpClsMain.laf?csmSeq=1170&ccfNo=1&cciNo=1&cnpClsNo=1"
  ],
  "jaegebal-yeongeopjeji-bosan-yogeon": [
    "https://easylaw.go.kr/CSP/CnpClsMain.laf?csmSeq=1168&ccfNo=3&cciNo=2&cnpClsNo=3",
    "https://easylaw.go.kr/CSP/CnpClsMain.laf?csmSeq=1168&ccfNo=3&cciNo=2&cnpClsNo=4"
  ],
  "jaegebal-sangga-myeongdo-bosan-hyeobi": [
    "https://easylaw.go.kr/CSP/CnpClsMain.laf?csmSeq=1168&ccfNo=3&cciNo=2&cnpClsNo=1",
    "https://easylaw.go.kr/CSP/CnpClsMain.laf?csmSeq=1168&ccfNo=3&cciNo=2&cnpClsNo=3"
  ],
  "jaegebal-imsaigin-useondongbyang": [
    "https://easylaw.go.kr/CSP/CnpClsMain.laf?csmSeq=1168&ccfNo=4&cciNo=1&cnpClsNo=1",
    "https://easylaw.go.kr/CSP/CnpClsMain.laf?csmSeq=1168&ccfNo=4&cciNo=1&cnpClsNo=2"
  ],
  "sangga-imdaesaeobja-dansoonggyeongbiyul-bipyo": [
    "https://easylaw.go.kr/CSP/CnpClsMain.laf?csmSeq=627&ccfNo=3&cciNo=2&cnpClsNo=1"
  ],
  "sangga-imdaesaeobja-gamgasamgakbi-pillyogyeongbi": [
    "https://easylaw.go.kr/CSP/CnpClsMain.laf?csmSeq=627&ccfNo=3&cciNo=2&cnpClsNo=1"
  ],
  "sangga-imdaesaeobja-daechoolija-pillyogyeongbi": [
    "https://easylaw.go.kr/CSP/CnpClsMain.laf?csmSeq=627&ccfNo=3&cciNo=2&cnpClsNo=1"
  ],
  "sangga-imdaesaeobja-gamgasamgak-jonghap-bipyo": [
    "https://easylaw.go.kr/CSP/CnpClsMain.laf?csmSeq=627&ccfNo=3&cciNo=2&cnpClsNo=1"
  ],
  "sangga-imdaesaeobja-jonghapsodeukse-gyeongbi": [
    "https://easylaw.go.kr/CSP/CnpClsMain.laf?csmSeq=627&ccfNo=3&cciNo=2&cnpClsNo=1"
  ],
  "jikjangin-sangga-imdaesaeobja-deungrok-uimu": [
    "https://easylaw.go.kr/CSP/CnpClsMain.laf?csmSeq=627&ccfNo=3&cciNo=2&cnpClsNo=1",
    "https://easylaw.go.kr/CSP/CnpClsMain.laf?csmSeq=627&ccfNo=1&cciNo=2&cnpClsNo=1"
  ],
  "sangga-imdaesaeobja-bugase-ganjuimdaeryo": [
    "https://easylaw.go.kr/CSP/CnpClsMain.laf?csmSeq=627&ccfNo=3&cciNo=1&cnpClsNo=3",
    "https://easylaw.go.kr/CSP/CnpClsMain.laf?csmSeq=627&ccfNo=3&cciNo=2&cnpClsNo=1"
  ],
  "sangga-imdaesaeobja-bugase-hwanggeup": [
    "https://easylaw.go.kr/CSP/CnpClsMain.laf?csmSeq=627&ccfNo=3&cciNo=2&cnpClsNo=1",
    "https://easylaw.go.kr/CSP/CnpClsMain.laf?csmSeq=627&ccfNo=2&cciNo=1&cnpClsNo=1"
  ],
  "sangga-mudanjeonddae-gyeyakhaeji-yogeon": [
    "https://easylaw.go.kr/CSP/CnpClsMain.laf?csmSeq=627&ccfNo=3&cciNo=3&cnpClsNo=3",
    "https://easylaw.go.kr/CSP/CnpClsMain.laf?csmSeq=627&ccfNo=3&cciNo=3&cnpClsNo=1"
  ],
  "sangga-jeondaecha-jeonchaiin-boho": [
    "https://easylaw.go.kr/CSP/CnpClsMain.laf?csmSeq=627&ccfNo=3&cciNo=3&cnpClsNo=3"
  ],
  "sangga-jeondaecha-imdaein-seomyeon-yogeon": [
    "https://easylaw.go.kr/CSP/CnpClsMain.laf?csmSeq=627&ccfNo=3&cciNo=3&cnpClsNo=3"
  ],
  "sangga-ibo-jeonddae-dongui-bupillyeo": [
    "https://easylaw.go.kr/CSP/CnpClsMain.laf?csmSeq=627&ccfNo=3&cciNo=3&cnpClsNo=3"
  ],
  "sangga-jeondaecha-habi-jeonchaiin-boho": [
    "https://easylaw.go.kr/CSP/CnpClsMain.laf?csmSeq=627&ccfNo=3&cciNo=3&cnpClsNo=3"
  ],
  "sangga-ibju-jeon-haja-imdaein-suriuimu": [
    "https://easylaw.go.kr/CSP/CnpClsMain.laf?csmSeq=627&ccfNo=3&cciNo=2&cnpClsNo=1",
    "https://easylaw.go.kr/CSP/CnpClsMain.laf?csmSeq=627&ccfNo=3&cciNo=1&cnpClsNo=1"
  ],
  "sangga-seonbu-teugak-imsaigin-budaam": [
    "https://easylaw.go.kr/CSP/CnpClsMain.laf?csmSeq=627&ccfNo=3&cciNo=2&cnpClsNo=2",
    "https://easylaw.go.kr/CSP/CnpClsMain.laf?csmSeq=627&ccfNo=3&cciNo=2&cnpClsNo=1"
  ],
  "sangga-haja-chaim-georjeol-ganeung": [
    "https://easylaw.go.kr/CSP/CnpClsMain.laf?csmSeq=627&ccfNo=3&cciNo=2&cnpClsNo=1",
    "https://easylaw.go.kr/CSP/CnpClsMain.laf?csmSeq=627&ccfNo=3&cciNo=1&cnpClsNo=1"
  ],
  "sangga-imdaecha-bunjeongjojeong-sincheng": [
    "https://easylaw.go.kr/CSP/CnpClsMain.laf?csmSeq=627&ccfNo=4&cciNo=2&cnpClsNo=3"
  ],
  "sangga-bunjeongjojeong-biyong-sosong-bipyo": [
    "https://easylaw.go.kr/CSP/CnpClsMain.laf?csmSeq=627&ccfNo=4&cciNo=2&cnpClsNo=3"
  ],
  "sangga-jojeongwseo-gangjejibhaeng": [
    "https://easylaw.go.kr/CSP/CnpClsMain.laf?csmSeq=627&ccfNo=4&cciNo=2&cnpClsNo=3",
    "https://easylaw.go.kr/CSP/CnpClsMain.laf?csmSeq=627&ccfNo=4&cciNo=2&cnpClsNo=4"
  ],
  "sangga-imdaein-bunjeongjojeong-bulloung": [
    "https://easylaw.go.kr/CSP/CnpClsMain.laf?csmSeq=627&ccfNo=4&cciNo=2&cnpClsNo=3"
  ],
  "sangga-yangsodeukse-janggiboyu-gongje": [
    "https://easylaw.go.kr/CSP/CnpClsMain.laf?csmSeq=627&ccfNo=3&cciNo=2&cnpClsNo=1"
  ],
  "sangga-dangigyodo-junggwaseyul": [
    "https://easylaw.go.kr/CSP/CnpClsMain.laf?csmSeq=627&ccfNo=3&cciNo=2&cnpClsNo=1"
  ],
  "sangga-gyeomubjuteog-yangdosodeukse": [
    "https://easylaw.go.kr/CSP/CnpClsMain.laf?csmSeq=627&ccfNo=3&cciNo=2&cnpClsNo=1"
  ],
  "sangga-maemae-bugase-pogwal-pyogi": [
    "https://easylaw.go.kr/CSP/CnpClsMain.laf?csmSeq=627&ccfNo=3&cciNo=2&cnpClsNo=1"
  ],
  "sangga-chwideukse-sigahaejunamaek-gyesan": [
    "https://easylaw.go.kr/CSP/CnpClsMain.laf?csmSeq=627&ccfNo=2&cciNo=1&cnpClsNo=2",
    "https://easylaw.go.kr/CSP/CnpClsMain.laf?csmSeq=627&ccfNo=2&cciNo=1&cnpClsNo=3"
  ],
  "sangga-bubu-gongdonmyeongui-chwideukse": [
    "https://easylaw.go.kr/CSP/CnpClsMain.laf?csmSeq=627&ccfNo=2&cciNo=2&cnpClsNo=1",
    "https://easylaw.go.kr/CSP/CnpClsMain.laf?csmSeq=627&ccfNo=3&cciNo=2&cnpClsNo=1"
  ],
  "sangga-bojeunggeum-banhwan-naeyongjeungmyeong": [
    "https://easylaw.go.kr/CSP/CnpClsMain.laf?csmSeq=627&ccfNo=4&cciNo=2&cnpClsNo=1",
    "https://easylaw.go.kr/CSP/CnpClsMain.laf?csmSeq=627&ccfNo=4&cciNo=1&cnpClsNo=1"
  ],
  "sangga-jeonse-gwon-saeupja-bihyo": [
    "https://easylaw.go.kr/CSP/CnpClsMain.laf?csmSeq=627&ccfNo=2&cciNo=3&cnpClsNo=1",
    "https://easylaw.go.kr/CSP/CnpClsMain.laf?csmSeq=627&ccfNo=2&cciNo=3&cnpClsNo=2"
  ],
  "sangga-imdaecha-gyeongmae-baedang-sunwi": [
    "https://easylaw.go.kr/CSP/CnpClsMain.laf?csmSeq=627&ccfNo=4&cciNo=2&cnpClsNo=2",
    "https://easylaw.go.kr/CSP/CnpClsMain.laf?csmSeq=627&ccfNo=2&cciNo=3&cnpClsNo=1"
  ],
  "sangga-gwolligeum-hoesu-bang-hae-yuhyeong": [
    "https://easylaw.go.kr/CSP/CnpClsMain.laf?csmSeq=627&ccfNo=4&cciNo=3&cnpClsNo=3"
  ],
  "gwolligeum-somelsiho-3nyeon-gisanil": [
    "https://easylaw.go.kr/CSP/CnpClsMain.laf?csmSeq=627&ccfNo=4&cciNo=3&cnpClsNo=3"
  ],
  "sangga-gwolligeum-sosong-ipjeung-seoryu": [
    "https://easylaw.go.kr/CSP/CnpClsMain.laf?csmSeq=627&ccfNo=4&cciNo=3&cnpClsNo=3"
  ],
  "gwolligeum-yeongeobgwon-sisel-gyeyak-cha": [
    "https://easylaw.go.kr/CSP/CnpClsMain.laf?csmSeq=627&ccfNo=4&cciNo=3&cnpClsNo=3"
  ],
  "imdaein-jaegeonsuk-gwolligeum-georjeol-yogeon": [
    "https://easylaw.go.kr/CSP/CnpClsMain.laf?csmSeq=627&ccfNo=4&cciNo=3&cnpClsNo=3",
    "https://easylaw.go.kr/CSP/CnpClsMain.laf?csmSeq=1170&ccfNo=1&cciNo=1&cnpClsNo=2"
  ],
  "sangga-10nyeon-gwolligeum-boho-jeok-yong": [
    "https://easylaw.go.kr/CSP/CnpClsMain.laf?csmSeq=627&ccfNo=4&cciNo=3&cnpClsNo=3",
    "https://easylaw.go.kr/CSP/CnpClsMain.laf?csmSeq=627&ccfNo=3&cciNo=4&cnpClsNo=3"
  ],
  "sangga-gwolligeum-pyojun-gyeyakseo-jagseong": [
    "https://easylaw.go.kr/CSP/CnpClsMain.laf?csmSeq=627&ccfNo=4&cciNo=3&cnpClsNo=3"
  ],
  "imdaein-gwado-imdaeryo-gwolligeum-bang-hae": [
    "https://easylaw.go.kr/CSP/CnpClsMain.laf?csmSeq=627&ccfNo=4&cciNo=3&cnpClsNo=3",
    "https://easylaw.go.kr/CSP/CnpClsMain.laf?csmSeq=627&ccfNo=3&cciNo=1&cnpClsNo=2"
  ],
  "gwolligeum-bang-hae-naeyongjeungmyeong-seuiyo": [
    "https://easylaw.go.kr/CSP/CnpClsMain.laf?csmSeq=627&ccfNo=4&cciNo=3&cnpClsNo=3"
  ],
  "sangga-gwolligeum-juseon-silpae-imdaein-bang-hae": [
    "https://easylaw.go.kr/CSP/CnpClsMain.laf?csmSeq=627&ccfNo=4&cciNo=3&cnpClsNo=3"
  ],
  "sangga-gyeyakgaesinyogugwon-10nyeon-gisanil": [
    "https://easylaw.go.kr/CSP/CnpClsMain.laf?csmSeq=627&ccfNo=3&cciNo=4&cnpClsNo=3"
  ],
  "sangga-imdaein-gaeshin-georjeol-tonbo-sigi": [
    "https://easylaw.go.kr/CSP/CnpClsMain.laf?csmSeq=627&ccfNo=3&cciNo=4&cnpClsNo=3"
  ],
  "sangga-imdaeryo-jeunggaek-5percent-jeyhan": [
    "https://easylaw.go.kr/CSP/CnpClsMain.laf?csmSeq=627&ccfNo=3&cciNo=1&cnpClsNo=2",
    "https://easylaw.go.kr/CSP/CnpClsMain.laf?csmSeq=627&ccfNo=3&cciNo=4&cnpClsNo=3"
  ],
  "sangga-muksijeok-gaeshin-haiji-imsaigin-tonbo": [
    "https://easylaw.go.kr/CSP/CnpClsMain.laf?csmSeq=627&ccfNo=3&cciNo=4&cnpClsNo=2"
  ],
  "sangga-jaegeonsuk-gyehoek-goji-gaeshin-georjeol": [
    "https://easylaw.go.kr/CSP/CnpClsMain.laf?csmSeq=627&ccfNo=3&cciNo=4&cnpClsNo=3",
    "https://easylaw.go.kr/CSP/CnpClsMain.laf?csmSeq=1170&ccfNo=1&cciNo=1&cnpClsNo=1"
  ],
  "sangga-chaimyeonche-3gi-gaeshin-georjeol-jogeon": [
    "https://easylaw.go.kr/CSP/CnpClsMain.laf?csmSeq=627&ccfNo=3&cciNo=4&cnpClsNo=3"
  ],
  "sangga-hwansan-chogwa-imdaeryo-inang-hyeob-ui": [
    "https://easylaw.go.kr/CSP/CnpClsMain.laf?csmSeq=627&ccfNo=3&cciNo=1&cnpClsNo=2",
    "https://easylaw.go.kr/CSP/CnpClsMain.laf?csmSeq=627&ccfNo=1&cciNo=2&cnpClsNo=1"
  ],
  "sangga-gyeyakgaesin-yogug-haengsa-gigan": [
    "https://easylaw.go.kr/CSP/CnpClsMain.laf?csmSeq=627&ccfNo=3&cciNo=4&cnpClsNo=3"
  ],
  "sangga-myeongdo-sosong-soyo-gigan-biyong": [
    "https://easylaw.go.kr/CSP/CnpClsMain.laf?csmSeq=627&ccfNo=4&cciNo=2&cnpClsNo=4",
    "https://easylaw.go.kr/CSP/CnpClsMain.laf?csmSeq=627&ccfNo=4&cciNo=2&cnpClsNo=3"
  ],
  "sangga-chaimyeonche-3gi-gyeyakhaejie-yogeon": [
    "https://easylaw.go.kr/CSP/CnpClsMain.laf?csmSeq=627&ccfNo=4&cciNo=1&cnpClsNo=1"
  ],
  "sangga-myeongdo-gangjejibe-jeolcha-jiphaengwan": [
    "https://easylaw.go.kr/CSP/CnpClsMain.laf?csmSeq=627&ccfNo=4&cciNo=2&cnpClsNo=4"
  ],
  "sangga-jesojeong-hwahae-joseo-gangjejibe": [
    "https://easylaw.go.kr/CSP/CnpClsMain.laf?csmSeq=627&ccfNo=4&cciNo=2&cnpClsNo=3"
  ],
  "sangga-wongsangboggu-beomwi-imsaigin-uimu": [
    "https://easylaw.go.kr/CSP/CnpClsMain.laf?csmSeq=627&ccfNo=4&cciNo=3&cnpClsNo=1",
    "https://easylaw.go.kr/CSP/CnpClsMain.laf?csmSeq=627&ccfNo=4&cciNo=3&cnpClsNo=2"
  ],
  "sangga-bojeunggeum-gongje-mihap-imdaeryo": [
    "https://easylaw.go.kr/CSP/CnpClsMain.laf?csmSeq=627&ccfNo=4&cciNo=1&cnpClsNo=1"
  ],
  "sangga-imsaigin-pasan-hoesaeng-myeongdo": [
    "https://easylaw.go.kr/CSP/CnpClsMain.laf?csmSeq=627&ccfNo=4&cciNo=2&cnpClsNo=2",
    "https://easylaw.go.kr/CSP/CnpClsMain.laf?csmSeq=627&ccfNo=4&cciNo=2&cnpClsNo=4"
  ],
  "sangga-jeomyu-ijeonggeumji-gacheobun-gongtak": [
    "https://easylaw.go.kr/CSP/CnpClsMain.laf?csmSeq=627&ccfNo=4&cciNo=2&cnpClsNo=4",
    "https://easylaw.go.kr/CSP/CnpClsMain.laf?csmSeq=627&ccfNo=4&cciNo=2&cnpClsNo=3"
  ],
  "sangga-gwoligeum-gitasodeuk-pillyogyeongbi": [
    "https://easylaw.go.kr/CSP/CnpClsMain.laf?csmSeq=627&ccfNo=4&cciNo=3&cnpClsNo=3"
  ],
  "gwoligeum-bugase-segeumgyesan-pogwal": [
    "https://easylaw.go.kr/CSP/CnpClsMain.laf?csmSeq=627&ccfNo=4&cciNo=3&cnpClsNo=3"
  ],
  "gwoligeum-weoncheongjingsu-gyesan-yangsu": [
    "https://easylaw.go.kr/CSP/CnpClsMain.laf?csmSeq=627&ccfNo=4&cciNo=3&cnpClsNo=3"
  ],
  "gwoligeum-yangdosodeukse-gyesan-bigyo": [
    "https://easylaw.go.kr/CSP/CnpClsMain.laf?csmSeq=627&ccfNo=4&cciNo=3&cnpClsNo=3"
  ],
  "gwoligeum-pogwal-yangsu-yopgeon-byeol": [
    "https://easylaw.go.kr/CSP/CnpClsMain.laf?csmSeq=627&ccfNo=4&cciNo=3&cnpClsNo=3"
  ],
  "gwoligeum-yeongeoprwon-gamgasamgak-yangsu": [
    "https://easylaw.go.kr/CSP/CnpClsMain.laf?csmSeq=627&ccfNo=4&cciNo=3&cnpClsNo=3"
  ],
  "sangga-gwoligeum-muryo-semujo": [
    "https://easylaw.go.kr/CSP/CnpClsMain.laf?csmSeq=627&ccfNo=4&cciNo=3&cnpClsNo=3"
  ],
  "gwoligeum-bunnigwasei-seonaek-gitasodeuk": [
    "https://easylaw.go.kr/CSP/CnpClsMain.laf?csmSeq=627&ccfNo=4&cciNo=3&cnpClsNo=3"
  ],
  "gwoligeum-se-yangdoin-yangsu-bigyo": [
    "https://easylaw.go.kr/CSP/CnpClsMain.laf?csmSeq=627&ccfNo=4&cciNo=3&cnpClsNo=3"
  ],
  "gwoligeum-gamjeongpyeong-yeongeoprwon-se": [
    "https://easylaw.go.kr/CSP/CnpClsMain.laf?csmSeq=627&ccfNo=4&cciNo=3&cnpClsNo=3"
  ],
  "gwoligeum-musingo-booliyik-gasan": [
    "https://easylaw.go.kr/CSP/CnpClsMain.laf?csmSeq=627&ccfNo=4&cciNo=3&cnpClsNo=3"
  ],

  "_730_주택연금": "https://easylaw.go.kr/CSP/CsmMain.laf?csmSeq=730",
  "reverse-mortgage-pledge-trust-method-difference-succession": [
    "https://easylaw.go.kr/CSP/CnpClsMain.laf?csmSeq=730&ccfNo=1&cciNo=1&cnpClsNo=1"
  ],
  "reverse-mortgage-benefits-spouse-death-full-pension-heir-protection": [
    "https://easylaw.go.kr/CSP/CnpClsMain.laf?csmSeq=730&ccfNo=1&cciNo=1&cnpClsNo=2"
  ],
  "reverse-mortgage-age-55-couple-eligibility-guardianship-proxy": [
    "https://easylaw.go.kr/CSP/CnpClsMain.laf?csmSeq=730&ccfNo=2&cciNo=1&cnpClsNo=1"
  ],
  "reverse-mortgage-property-12billion-limit-officetel-mixeduse": [
    "https://easylaw.go.kr/CSP/CnpClsMain.laf?csmSeq=730&ccfNo=2&cciNo=1&cnpClsNo=2"
  ],
  "reverse-mortgage-two-home-combined-12billion-disposal-condition": [
    "https://easylaw.go.kr/CSP/CnpClsMain.laf?csmSeq=730&ccfNo=2&cciNo=1&cnpClsNo=3"
  ],
  "reverse-mortgage-application-process-documents-rescission-period": [
    "https://easylaw.go.kr/CSP/CnpClsMain.laf?csmSeq=730&ccfNo=2&cciNo=2&cnpClsNo=1"
  ],
  "reverse-mortgage-initial-annual-guarantee-fee-registration-cost": [
    "https://easylaw.go.kr/CSP/CnpClsMain.laf?csmSeq=730&ccfNo=2&cciNo=2&cnpClsNo=2"
  ],
  "reverse-mortgage-property-tax-license-tax-reduction-interest-deduction": [
    "https://easylaw.go.kr/CSP/CnpClsMain.laf?csmSeq=730&ccfNo=2&cciNo=3&cnpClsNo=1"
  ],
  "reverse-mortgage-payment-method-lifetime-fixed-term-growth-type": [
    "https://easylaw.go.kr/CSP/CnpClsMain.laf?csmSeq=730&ccfNo=3&cciNo=1&cnpClsNo=1"
  ],
  "child-support-nonresident-parent-obligation-past-claim-retroactive": [
    "https://easylaw.go.kr/CSP/CnpClsMain.laf?csmSeq=233&ccfNo=5&cciNo=3&cnpClsNo=1"
  ],
  "child-support-parental-agreement-court-determination-modification": [
    "https://easylaw.go.kr/CSP/CnpClsMain.laf?csmSeq=233&ccfNo=5&cciNo=3&cnpClsNo=1"
  ],
  "child-support-agency-role-service-priority-target-application": [
    "https://easylaw.go.kr/CSP/CnpClsMain.laf?csmSeq=233&ccfNo=5&cciNo=3&cnpClsNo=1"
  ],
  "child-support-agency-agreement-support-visitation-notarization": [
    "https://easylaw.go.kr/CSP/CnpClsMain.laf?csmSeq=233&ccfNo=5&cciNo=3&cnpClsNo=1"
  ],
  "child-support-agency-legal-aid-lawsuit-acknowledgment-enforcement": [
    "https://easylaw.go.kr/CSP/CnpClsMain.laf?csmSeq=233&ccfNo=5&cciNo=3&cnpClsNo=3"
  ],
  "child-support-debt-collection-support-application-documents": [
    "https://easylaw.go.kr/CSP/CnpClsMain.laf?csmSeq=233&ccfNo=5&cciNo=3&cnpClsNo=3"
  ],
  "child-support-advance-payment-150pct-income-monthly-20万": [
    "https://easylaw.go.kr/CSP/CnpClsMain.laf?csmSeq=233&ccfNo=5&cciNo=3&cnpClsNo=3"
  ],
  "child-support-nonpayment-fine-detention-order-penalty": [
    "https://easylaw.go.kr/CSP/CnpClsMain.laf?csmSeq=1659&ccfNo=3&cciNo=1&cnpClsNo=1"
  ],
  "child-support-nonpayment-drivers-license-suspension-revocation": [
    "https://easylaw.go.kr/CSP/CnpClsMain.laf?csmSeq=1659&ccfNo=3&cciNo=1&cnpClsNo=2"
  ],
  "child-support-nonpayment-exit-ban-request-condition-release": [
    "https://easylaw.go.kr/CSP/CnpClsMain.laf?csmSeq=1659&ccfNo=3&cciNo=1&cnpClsNo=3"
  ],
  "child-support-defaulter-name-disclosure-application-exclusion": [
    "https://easylaw.go.kr/CSP/CnpClsMain.laf?csmSeq=1659&ccfNo=3&cciNo=1&cnpClsNo=4"
  ],

  "_2588_보험계약자": "https://easylaw.go.kr/CSP/CsmMain.laf?csmSeq=2588",
  "insurance-protection-savings-type-difference-parties-roles": [
    "https://easylaw.go.kr/CSP/CnpClsMain.laf?csmSeq=2588&ccfNo=1&cciNo=1&cnpClsNo=1"
  ],
  "insurance-renewable-nonrenewable-premium-pros-cons-channel-selection": [
    "https://easylaw.go.kr/CSP/CnpClsMain.laf?csmSeq=2588&ccfNo=2&cciNo=1&cnpClsNo=1"
  ],
  "special-building-fire-insurance-30days-mandatory-auto-liability-penalty": [
    "https://easylaw.go.kr/CSP/CnpClsMain.laf?csmSeq=2588&ccfNo=2&cciNo=1&cnpClsNo=3"
  ],
  "insurance-accident-notification-duty-delay-claim-processing-steps": [
    "https://easylaw.go.kr/CSP/CnpClsMain.laf?csmSeq=2588&ccfNo=3&cciNo=1&cnpClsNo=1"
  ],
  "life-insurance-death-disability-payment-grounds-medical-indemnity-coverage": [
    "https://easylaw.go.kr/CSP/CnpClsMain.laf?csmSeq=2588&ccfNo=3&cciNo=1&cnpClsNo=2"
  ],
  "daily-construction-worker-definition-3months-continuous-employment": [
    "https://easylaw.go.kr/CSP/CnpClsMain.laf?csmSeq=1002&ccfNo=1&cciNo=1&cnpClsNo=1"
  ],
  "daily-construction-worker-worknet-job-search-fake-ad-reporting": [
    "https://easylaw.go.kr/CSP/CnpClsMain.laf?csmSeq=1002&ccfNo=1&cciNo=2&cnpClsNo=1"
  ],
  "construction-daily-worker-2026-minimum-wage-contractor-joint-liability": [
    "https://easylaw.go.kr/CSP/CnpClsMain.laf?csmSeq=1002&ccfNo=2&cciNo=1&cnpClsNo=1"
  ],
  "construction-daily-worker-weekly-40hrs-daily-8hrs-overtime-approval": [
    "https://easylaw.go.kr/CSP/CnpClsMain.laf?csmSeq=1002&ccfNo=2&cciNo=1&cnpClsNo=2"
  ],
  "construction-daily-worker-written-contract-mandatory-items-prohibited-clauses": [
    "https://easylaw.go.kr/CSP/CnpClsMain.laf?csmSeq=1002&ccfNo=2&cciNo=2&cnpClsNo=1"
  ],
  "insurance-exemption-intentional-gross-negligence-drunk-driving-self-harm": [
    "https://easylaw.go.kr/CSP/CnpClsMain.laf?csmSeq=2588&ccfNo=3&cciNo=2&cnpClsNo=1"
  ],
  "insurance-fraud-types-deliberate-accident-fake-diagnosis-auto-fraud-response": [
    "https://easylaw.go.kr/CSP/CnpClsMain.laf?csmSeq=2588&ccfNo=3&cciNo=2&cnpClsNo=2"
  ],
  "insurance-policy-withdrawal-15days-30days-limit-cancellation-refund": [
    "https://easylaw.go.kr/CSP/CnpClsMain.laf?csmSeq=2588&ccfNo=4&cciNo=1&cnpClsNo=1"
  ],
  "insurance-contract-void-grounds-minor-consent-premium-default-termination": [
    "https://easylaw.go.kr/CSP/CnpClsMain.laf?csmSeq=2588&ccfNo=4&cciNo=1&cnpClsNo=2"
  ],
  "insurance-lapse-revival-3years-reinstatement-overdue-premium-coverage-date": [
    "https://easylaw.go.kr/CSP/CnpClsMain.laf?csmSeq=2588&ccfNo=4&cciNo=2&cnpClsNo=1"
  ],
  "insurance-financial-dispute-mediation-committee-consumer-agency-selection": [
    "https://easylaw.go.kr/CSP/CnpClsMain.laf?csmSeq=2588&ccfNo=5&cciNo=1&cnpClsNo=1"
  ],
  "insurance-civil-lawsuit-court-claim-steps-mediation-agreement-legal-effect": [
    "https://easylaw.go.kr/CSP/CnpClsMain.laf?csmSeq=2588&ccfNo=5&cciNo=1&cnpClsNo=2"
  ],
  "dismissal-vs-resignation-employment-termination-difference-effective-date": [
    "https://easylaw.go.kr/CSP/CnpClsMain.laf?csmSeq=514&ccfNo=1&cciNo=1&cnpClsNo=1"
  ],
  "labor-standards-act-dismissal-grounds-procedure-scope-unfair-dismissal-remedy": [
    "https://easylaw.go.kr/CSP/CnpClsMain.laf?csmSeq=514&ccfNo=1&cciNo=1&cnpClsNo=2"
  ],
  "dismissal-ban-labor-law-report-retaliation-sexual-harassment-victim-protection": [
    "https://easylaw.go.kr/CSP/CnpClsMain.laf?csmSeq=514&ccfNo=3&cciNo=1&cnpClsNo=1"
  ],
  "dismissal-ban-work-injury-recovery-maternity-leave-parental-leave-protection": [
    "https://easylaw.go.kr/CSP/CnpClsMain.laf?csmSeq=514&ccfNo=4&cciNo=1&cnpClsNo=1"
  ],
  "advance-dismissal-notice-30days-obligation-notice-pay-exemption-grounds": [
    "https://easylaw.go.kr/CSP/CnpClsMain.laf?csmSeq=514&ccfNo=4&cciNo=2&cnpClsNo=1"
  ],

  "_1286_개인워크아웃": "https://easylaw.go.kr/CSP/CsmMain.laf?csmSeq=1286",
  "_616_개인파산": "https://easylaw.go.kr/CSP/CsmMain.laf?csmSeq=616",
  "personal-rehabilitation-vs-bankruptcy": [
    "https://easylaw.go.kr/CSP/CnpClsMain.laf?csmSeq=1286&ccfNo=1&cciNo=1&cnpClsNo=1"
  ],
  "personal-bankruptcy-non-dischargeable-debts": [
    "https://easylaw.go.kr/CSP/CnpClsMain.laf?csmSeq=616&ccfNo=1&cciNo=1&cnpClsNo=1"
  ],
  "personal-rehabilitation-guarantor-liability": [
    "https://easylaw.go.kr/CSP/CnpClsMain.laf?csmSeq=1286&ccfNo=5&cciNo=1&cnpClsNo=2"
  ],
  "personal-rehabilitation-credit-recovery-timeline": [
    "https://easylaw.go.kr/CSP/CnpClsMain.laf?csmSeq=1286&ccfNo=1&cciNo=1&cnpClsNo=1"
  ],
  "workout-income-jobless-condition": [
    "https://easylaw.go.kr/CSP/CnpClsMain.laf?csmSeq=1286&ccfNo=1&cciNo=1&cnpClsNo=1"
  ],
  "workout-charged-off-loan-reduction-rate": [
    "https://easylaw.go.kr/CSP/CnpClsMain.laf?csmSeq=1286&ccfNo=1&cciNo=1&cnpClsNo=1"
  ],
  "debt-adjustment-3types-comparison": [
    "https://easylaw.go.kr/CSP/CnpClsMain.laf?csmSeq=1286&ccfNo=1&cciNo=1&cnpClsNo=1"
  ],
  "workout-interest-relief-monthly-payment": [
    "https://easylaw.go.kr/CSP/CnpClsMain.laf?csmSeq=1286&ccfNo=1&cciNo=1&cnpClsNo=1"
  ],
  "workout-debt-scope-nonmember-lender": [
    "https://easylaw.go.kr/CSP/CnpClsMain.laf?csmSeq=1286&ccfNo=1&cciNo=1&cnpClsNo=1"
  ],
  "workout-revival-after-default": [
    "https://easylaw.go.kr/CSP/CnpClsMain.laf?csmSeq=1286&ccfNo=1&cciNo=1&cnpClsNo=1"
  ],
  "workout-credit-record-deletion": [
    "https://easylaw.go.kr/CSP/CnpClsMain.laf?csmSeq=1286&ccfNo=1&cciNo=1&cnpClsNo=1"
  ],
  "personal-rehabilitation-to-workout-conversion": [
    "https://easylaw.go.kr/CSP/CnpClsMain.laf?csmSeq=1286&ccfNo=1&cciNo=1&cnpClsNo=1"
  ],
  "workout-vulnerable-class-90percent-reduction": [
    "https://easylaw.go.kr/CSP/CnpClsMain.laf?csmSeq=1286&ccfNo=1&cciNo=1&cnpClsNo=1"
  ],
  "preworkout-interest-rate-reduction": [
    "https://easylaw.go.kr/CSP/CnpClsMain.laf?csmSeq=1286&ccfNo=1&cciNo=1&cnpClsNo=1"
  ],
  "workout-application-documents-income-proof": [
    "https://easylaw.go.kr/CSP/CnpClsMain.laf?csmSeq=1286&ccfNo=1&cciNo=1&cnpClsNo=1"
  ],
  "workout-enforcement-suspension-guarantor": [
    "https://easylaw.go.kr/CSP/CnpClsMain.laf?csmSeq=1286&ccfNo=1&cciNo=1&cnpClsNo=1"
  ],
  "ccrs-debt-adjustment-fee-procedure": [
    "https://easylaw.go.kr/CSP/CnpClsMain.laf?csmSeq=1286&ccfNo=1&cciNo=1&cnpClsNo=1"
  ],
  "workout-secured-debt-interest-relief": [
    "https://easylaw.go.kr/CSP/CnpClsMain.laf?csmSeq=1286&ccfNo=1&cciNo=1&cnpClsNo=1"
  ],
  "workout-youth-incentive-extra-reduction": [
    "https://easylaw.go.kr/CSP/CnpClsMain.laf?csmSeq=1286&ccfNo=1&cciNo=1&cnpClsNo=1"
  ],
  "workout-microloan-living-expenses": [
    "https://easylaw.go.kr/CSP/CnpClsMain.laf?csmSeq=1286&ccfNo=1&cciNo=1&cnpClsNo=1"
  ],
  "rapid-debt-adjustment-30days-eligibility": [
    "https://easylaw.go.kr/CSP/CnpClsMain.laf?csmSeq=1286&ccfNo=1&cciNo=1&cnpClsNo=1"
  ],
  "pre-workout-income-employment-rate": [
    "https://easylaw.go.kr/CSP/CnpClsMain.laf?csmSeq=1286&ccfNo=1&cciNo=1&cnpClsNo=1"
  ],
  "personal-workout-90days-repayment-structure": [
    "https://easylaw.go.kr/CSP/CnpClsMain.laf?csmSeq=1286&ccfNo=1&cciNo=1&cnpClsNo=1"
  ],
  "debt-adjustment-eligibility-exclusion": [
    "https://easylaw.go.kr/CSP/CnpClsMain.laf?csmSeq=1286&ccfNo=1&cciNo=1&cnpClsNo=1"
  ],
  "ccrs-covered-debt-scope-transferred": [
    "https://easylaw.go.kr/CSP/CnpClsMain.laf?csmSeq=1286&ccfNo=1&cciNo=1&cnpClsNo=1"
  ],
  "no-delinquency-record-debt-check": [
    "https://easylaw.go.kr/CSP/CnpClsMain.laf?csmSeq=1286&ccfNo=1&cciNo=1&cnpClsNo=1"
  ],
  "tax-arrears-debt-adjustment-alternative": [
    "https://easylaw.go.kr/CSP/CnpClsMain.laf?csmSeq=1286&ccfNo=1&cciNo=1&cnpClsNo=1"
  ],
  "minimum-livelihood-income-workout-apply": [
    "https://easylaw.go.kr/CSP/CnpClsMain.laf?csmSeq=1286&ccfNo=1&cciNo=1&cnpClsNo=1"
  ],
  "income-proof-alternative-docs-rental": [
    "https://easylaw.go.kr/CSP/CnpClsMain.laf?csmSeq=1286&ccfNo=1&cciNo=1&cnpClsNo=1"
  ],
  "auction-property-debt-adjustment-lien": [
    "https://easylaw.go.kr/CSP/CnpClsMain.laf?csmSeq=1286&ccfNo=1&cciNo=1&cnpClsNo=1"
  ],
  "wage-garnishment-workout-public-rental": [
    "https://easylaw.go.kr/CSP/CnpClsMain.laf?csmSeq=1286&ccfNo=1&cciNo=1&cnpClsNo=1"
  ],
  "guarantee-mortgage-loan-debt-adjustment": [
    "https://easylaw.go.kr/CSP/CnpClsMain.laf?csmSeq=1286&ccfNo=1&cciNo=1&cnpClsNo=1"
  ],
  "vehicle-disposal-workplace-notification": [
    "https://easylaw.go.kr/CSP/CnpClsMain.laf?csmSeq=1286&ccfNo=1&cciNo=1&cnpClsNo=1"
  ],
  "debt-adjustment-documents-consultation": [
    "https://easylaw.go.kr/CSP/CnpClsMain.laf?csmSeq=1286&ccfNo=1&cciNo=1&cnpClsNo=1"
  ],
  "debt-adjustment-confirmation-dissent-creditor": [
    "https://easylaw.go.kr/CSP/CnpClsMain.laf?csmSeq=1286&ccfNo=1&cciNo=1&cnpClsNo=1"
  ],
  "post-application-auto-transfer-deposit": [
    "https://easylaw.go.kr/CSP/CnpClsMain.laf?csmSeq=1286&ccfNo=1&cciNo=1&cnpClsNo=1"
  ],
  "workout-delinquency-release-guarantor": [
    "https://easylaw.go.kr/CSP/CnpClsMain.laf?csmSeq=1286&ccfNo=1&cciNo=1&cnpClsNo=1"
  ],
  "application-fee-missing-debt-collection-call": [
    "https://easylaw.go.kr/CSP/CnpClsMain.laf?csmSeq=1286&ccfNo=1&cciNo=1&cnpClsNo=1"
  ],
  "self-employed-card-sales-account-freeze": [
    "https://easylaw.go.kr/CSP/CnpClsMain.laf?csmSeq=1286&ccfNo=1&cciNo=1&cnpClsNo=1"
  ],
  "repayment-default-cancellation-lump-sum-account": [
    "https://easylaw.go.kr/CSP/CnpClsMain.laf?csmSeq=1286&ccfNo=1&cciNo=1&cnpClsNo=1"
  ],
  "workout-new-loan-card-insurance-surety": [
    "https://easylaw.go.kr/CSP/CnpClsMain.laf?csmSeq=1286&ccfNo=1&cciNo=1&cnpClsNo=1"
  ],
  "workout-asset-concealment-cancellation-restriction": [
    "https://easylaw.go.kr/CSP/CnpClsMain.laf?csmSeq=1286&ccfNo=1&cciNo=1&cnpClsNo=1"
  ],
  "individual-rehabilitation-income-debt-limit-procedure": [
    "https://easylaw.go.kr/CSP/CnpClsMain.laf?csmSeq=1286&ccfNo=1&cciNo=1&cnpClsNo=1"
  ],
  "rehabilitation-repayment-disposable-income-non-exempt-claims": [
    "https://easylaw.go.kr/CSP/CnpClsMain.laf?csmSeq=1286&ccfNo=1&cciNo=1&cnpClsNo=1"
  ],
  "personal-bankruptcy-eligibility-discharge-procedure": [
    "https://easylaw.go.kr/CSP/CnpClsMain.laf?csmSeq=616&ccfNo=1&cciNo=1&cnpClsNo=1"
  ],
  "bankruptcy-non-dischargeable-debts-discharge-denial": [
    "https://easylaw.go.kr/CSP/CnpClsMain.laf?csmSeq=616&ccfNo=1&cciNo=1&cnpClsNo=1"
  ],
  "ccrs-rehabilitation-bankruptcy-legal-support-eligibility": [
    "https://easylaw.go.kr/CSP/CnpClsMain.laf?csmSeq=1286&ccfNo=1&cciNo=1&cnpClsNo=1"
  ],
  "ccrs-microloan-program-post-debt-adjustment-eligibility": [
    "https://easylaw.go.kr/CSP/CnpClsMain.laf?csmSeq=1286&ccfNo=1&cciNo=1&cnpClsNo=1"
  ],
  "ccrs-microloan-online-application-documents-processing-time": [
    "https://easylaw.go.kr/CSP/CnpClsMain.laf?csmSeq=1286&ccfNo=1&cciNo=1&cnpClsNo=1"
  ],
  "personal-rehabilitation-repayment-calculation": [
    "https://easylaw.go.kr/CSP/CnpClsMain.laf?csmSeq=1286&ccfNo=1&cciNo=1&cnpClsNo=1"
  ],
  "personal-rehabilitation-living-expenses-2026": [
    "https://easylaw.go.kr/CSP/CnpClsMain.laf?csmSeq=1286&ccfNo=1&cciNo=1&cnpClsNo=1"
  ],
  "ccrs-microloan-interest-rate-limit-no-collateral": [
    "https://easylaw.go.kr/CSP/CnpClsMain.laf?csmSeq=1286&ccfNo=1&cciNo=1&cnpClsNo=1"
  ],
  "ccrs-microloan-repayment-date-change-early-payoff-autotransfer": [
    "https://easylaw.go.kr/CSP/CnpClsMain.laf?csmSeq=1286&ccfNo=1&cciNo=1&cnpClsNo=1"
  ],
  "ccrs-microloan-overdue-penalty-existing-delinquency": [
    "https://easylaw.go.kr/CSP/CnpClsMain.laf?csmSeq=1286&ccfNo=1&cciNo=1&cnpClsNo=1"
  ],
  "ccrs-microloan-additional-loan-payoff-refund-inquiry": [
    "https://easylaw.go.kr/CSP/CnpClsMain.laf?csmSeq=1286&ccfNo=1&cciNo=1&cnpClsNo=1"
  ],
  "ccrs-good-payer-credit-card-eligibility-exclusion": [
    "https://easylaw.go.kr/CSP/CnpClsMain.laf?csmSeq=1286&ccfNo=1&cciNo=1&cnpClsNo=1"
  ],
  "ccrs-credit-card-application-documents-online": [
    "https://easylaw.go.kr/CSP/CnpClsMain.laf?csmSeq=1286&ccfNo=1&cciNo=1&cnpClsNo=1"
  ],
  "ccrs-credit-card-limit-type-reissue": [
    "https://easylaw.go.kr/CSP/CnpClsMain.laf?csmSeq=1286&ccfNo=1&cciNo=1&cnpClsNo=1"
  ],
  "ccrs-digital-consultation-login-auth-agreement": [
    "https://easylaw.go.kr/CSP/CnpClsMain.laf?csmSeq=1286&ccfNo=1&cciNo=1&cnpClsNo=1"
  ],
  "ccrs-digital-consultation-program-setup": [
    "https://easylaw.go.kr/CSP/CnpClsMain.laf?csmSeq=1286&ccfNo=1&cciNo=1&cnpClsNo=1"
  ],
  "ccrs-visit-reservation-required-change-cancel-penalty": [
    "https://easylaw.go.kr/CSP/CnpClsMain.laf?csmSeq=1286&ccfNo=1&cciNo=1&cnpClsNo=1"
  ],
  "workout-public-info-early-removal-interest-rate": [
    "https://easylaw.go.kr/CSP/CnpClsMain.laf?csmSeq=1286&ccfNo=1&cciNo=1&cnpClsNo=1"
  ],
  "debt-lump-payoff-extra-reduction-benefits": [
    "https://easylaw.go.kr/CSP/CnpClsMain.laf?csmSeq=1286&ccfNo=1&cciNo=1&cnpClsNo=1"
  ],
  "good-payer-credit-score-rise-jump-program": [
    "https://easylaw.go.kr/CSP/CnpClsMain.laf?csmSeq=1286&ccfNo=1&cciNo=1&cnpClsNo=1"
  ],
  "debt-adjustment-lapse-readjustment-application": [
    "https://easylaw.go.kr/CSP/CnpClsMain.laf?csmSeq=1286&ccfNo=1&cciNo=1&cnpClsNo=1"
  ],
  "modification-revival-midterm-debt-exemption": [
    "https://easylaw.go.kr/CSP/CnpClsMain.laf?csmSeq=1286&ccfNo=1&cciNo=1&cnpClsNo=1"
  ],
  "mortgage-debt-adjustment-rate-period-difference": [
    "https://easylaw.go.kr/CSP/CnpClsMain.laf?csmSeq=1286&ccfNo=1&cciNo=1&cnpClsNo=1"
  ],
  "new-start-fund-sme-bad-debtor-ccrs-process": [
    "https://easylaw.go.kr/CSP/CnpClsMain.laf?csmSeq=1286&ccfNo=1&cciNo=1&cnpClsNo=1"
  ],
  "new-leap-fund-long-overdue-auto-purchase-loan": [
    "https://easylaw.go.kr/CSP/CnpClsMain.laf?csmSeq=1286&ccfNo=1&cciNo=1&cnpClsNo=1"
  ],
  "financial-institution-self-debt-adjustment-comparison": [
    "https://easylaw.go.kr/CSP/CnpClsMain.laf?csmSeq=1286&ccfNo=1&cciNo=1&cnpClsNo=1"
  ],
  "ccrs-financial-employment-welfare-combined-support": [
    "https://easylaw.go.kr/CSP/CnpClsMain.laf?csmSeq=1286&ccfNo=1&cciNo=1&cnpClsNo=1"
  ],
  "credit-welfare-consulting-sme-restart-support": [
    "https://easylaw.go.kr/CSP/CnpClsMain.laf?csmSeq=1286&ccfNo=1&cciNo=1&cnpClsNo=1"
  ],
  "ccrs-credit-education-online-free-visiting": [
    "https://easylaw.go.kr/CSP/CnpClsMain.laf?csmSeq=1286&ccfNo=1&cciNo=1&cnpClsNo=1"
  ],
  "illegal-lending-60pct-void-damage-report-process": [
    "https://easylaw.go.kr/CSP/CnpClsMain.laf?csmSeq=1286&ccfNo=1&cciNo=1&cnpClsNo=1"
  ],
  "personal-rehabilitation-application-procedure": [
    "https://easylaw.go.kr/CSP/CnpClsMain.laf?csmSeq=1286&ccfNo=1&cciNo=1&cnpClsNo=1"
  ],
  "personal-rehabilitation-creditor-meeting": [
    "https://easylaw.go.kr/CSP/CnpClsMain.laf?csmSeq=1286&ccfNo=1&cciNo=1&cnpClsNo=1"
  ],
  "personal-rehabilitation-free-legal-support": [
    "https://easylaw.go.kr/CSP/CnpClsMain.laf?csmSeq=1286&ccfNo=1&cciNo=1&cnpClsNo=1"
  ],
  "personal-rehabilitation-employment-disadvantage": [
    "https://easylaw.go.kr/CSP/CnpClsMain.laf?csmSeq=1286&ccfNo=1&cciNo=1&cnpClsNo=1"
  ],
  "self-employed-personal-rehabilitation": [
    "https://easylaw.go.kr/CSP/CnpClsMain.laf?csmSeq=1286&ccfNo=1&cciNo=1&cnpClsNo=1"
  ],
  "personal-rehabilitation-discharge-completion": [
    "https://easylaw.go.kr/CSP/CnpClsMain.laf?csmSeq=1286&ccfNo=1&cciNo=1&cnpClsNo=1"
  ],
  "personal-rehabilitation-procedure-dismissal": [
    "https://easylaw.go.kr/CSP/CnpClsMain.laf?csmSeq=1286&ccfNo=1&cciNo=1&cnpClsNo=1"
  ],
  "personal-bankruptcy-application-eligibility": [
    "https://easylaw.go.kr/CSP/CnpClsMain.laf?csmSeq=616&ccfNo=1&cciNo=1&cnpClsNo=1"
  ],
  "personal-bankruptcy-discharge-refusal-reasons": [
    "https://easylaw.go.kr/CSP/CnpClsMain.laf?csmSeq=616&ccfNo=1&cciNo=1&cnpClsNo=1"
  ],
  "personal-bankruptcy-qualification-restrictions": [
    "https://easylaw.go.kr/CSP/CnpClsMain.laf?csmSeq=616&ccfNo=1&cciNo=1&cnpClsNo=1"
  ],
  "personal-bankruptcy-application-procedure": [
    "https://easylaw.go.kr/CSP/CnpClsMain.laf?csmSeq=616&ccfNo=1&cciNo=1&cnpClsNo=1"
  ],
  "personal-bankruptcy-reinstatement": [
    "https://easylaw.go.kr/CSP/CnpClsMain.laf?csmSeq=616&ccfNo=1&cciNo=1&cnpClsNo=1"
  ],
  "personal-rehabilitation-post-discharge-credit": [
    "https://easylaw.go.kr/CSP/CnpClsMain.laf?csmSeq=1286&ccfNo=1&cciNo=1&cnpClsNo=1"
  ],
  "personal-rehabilitation-debt-ceiling": [
    "https://easylaw.go.kr/CSP/CnpClsMain.laf?csmSeq=1286&ccfNo=1&cciNo=1&cnpClsNo=1"
  ],
  "personal-rehabilitation-stay-enforcement": [
    "https://easylaw.go.kr/CSP/CnpClsMain.laf?csmSeq=1286&ccfNo=1&cciNo=1&cnpClsNo=1"
  ],
  "personal-rehabilitation-repayment-plan-change": [
    "https://easylaw.go.kr/CSP/CnpClsMain.laf?csmSeq=1286&ccfNo=1&cciNo=1&cnpClsNo=1"
  ],
  "personal-rehabilitation-liquidation-value": [
    "https://easylaw.go.kr/CSP/CnpClsMain.laf?csmSeq=1286&ccfNo=1&cciNo=1&cnpClsNo=1"
  ],
  "personal-bankruptcy-post-discharge-finance": [
    "https://easylaw.go.kr/CSP/CnpClsMain.laf?csmSeq=616&ccfNo=1&cciNo=1&cnpClsNo=1"
  ],
  "personal-rehabilitation-debt-reduction-rate": [
    "https://easylaw.go.kr/CSP/CnpClsMain.laf?csmSeq=1286&ccfNo=1&cciNo=1&cnpClsNo=1"
  ],
  "personal-rehabilitation-application-costs": [
    "https://easylaw.go.kr/CSP/CnpClsMain.laf?csmSeq=1286&ccfNo=1&cciNo=1&cnpClsNo=1"
  ],
  "personal-rehabilitation-private-debt-inclusion": [
    "https://easylaw.go.kr/CSP/CnpClsMain.laf?csmSeq=1286&ccfNo=1&cciNo=1&cnpClsNo=1"
  ],
  "personal-rehabilitation-secured-debt": [
    "https://easylaw.go.kr/CSP/CnpClsMain.laf?csmSeq=1286&ccfNo=1&cciNo=1&cnpClsNo=1"
  ],
  "personal-bankruptcy-simultaneous-closure": [
    "https://easylaw.go.kr/CSP/CnpClsMain.laf?csmSeq=616&ccfNo=1&cciNo=1&cnpClsNo=1"
  ],
  "employed-vs-selfemployed-rehabilitation": [
    "https://easylaw.go.kr/CSP/CnpClsMain.laf?csmSeq=1286&ccfNo=1&cciNo=1&cnpClsNo=1"
  ],
  "personal-rehabilitation-plan-approval": [
    "https://easylaw.go.kr/CSP/CnpClsMain.laf?csmSeq=1286&ccfNo=1&cciNo=1&cnpClsNo=1"
  ],
  "personal-bankruptcy-voluntary-vs-creditor": [
    "https://easylaw.go.kr/CSP/CnpClsMain.laf?csmSeq=616&ccfNo=1&cciNo=1&cnpClsNo=1"
  ],
  "workout-vs-personal-rehabilitation": [
    "https://easylaw.go.kr/CSP/CnpClsMain.laf?csmSeq=1286&ccfNo=1&cciNo=1&cnpClsNo=1"
  ],
  "personal-rehabilitation-car-liquidation-value": [
    "https://easylaw.go.kr/CSP/CnpClsMain.laf?csmSeq=1286&ccfNo=1&cciNo=1&cnpClsNo=1"
  ]
}